<annotation>
	<folder>train</folder>
	<filename>DGDl6EuXgAAi2T9.jpg</filename>
	<path>C:\Users\ASUS PC\Desktop\Automatic-Vehicle-Classification\models\research\object_detection\images\train\DGDl6EuXgAAi2T9.jpg</path>
	<source>
		<database>Unknown</database>
	</source>
	<size>
		<width>1200</width>
		<height>800</height>
		<depth>3</depth>
	</size>
	<segmented>0</segmented>
	<object>
		<name>motorbike</name>
		<pose>Unspecified</pose>
		<truncated>0</truncated>
		<difficult>0</difficult>
		<bndbox>
			<xmin>591</xmin>
			<ymin>455</ymin>
			<xmax>923</xmax>
			<ymax>642</ymax>
		</bndbox>
	</object>
</annotation>
