<annotation>
	<folder>train</folder>
	<filename>Hot-sale-in-Yemen-Tanzania-Mali-Togo.jpg</filename>
	<path>C:\Users\ASUS PC\Desktop\Automatic-Vehicle-Classification\models\research\object_detection\images\train\Hot-sale-in-Yemen-Tanzania-Mali-Togo.jpg</path>
	<source>
		<database>Unknown</database>
	</source>
	<size>
		<width>1000</width>
		<height>1000</height>
		<depth>3</depth>
	</size>
	<segmented>0</segmented>
	<object>
		<name>motorbike</name>
		<pose>Unspecified</pose>
		<truncated>0</truncated>
		<difficult>0</difficult>
		<bndbox>
			<xmin>26</xmin>
			<ymin>228</ymin>
			<xmax>973</xmax>
			<ymax>806</ymax>
		</bndbox>
	</object>
</annotation>
